README.rst
pef.py
setup.py
pef.egg-info/PKG-INFO
pef.egg-info/SOURCES.txt
pef.egg-info/dependency_links.txt
pef.egg-info/entry_points.txt
pef.egg-info/not-zip-safe
pef.egg-info/requires.txt
pef.egg-info/top_level.txt